LICENSE.md
MANIFEST.in
README.md
build_upload.md
pyproject.toml
setup.cfg
setup.py
src/selenium_profiles/__init__.py
src/selenium_profiles/webdriver.py
src/selenium_profiles.egg-info/PKG-INFO
src/selenium_profiles.egg-info/SOURCES.txt
src/selenium_profiles.egg-info/dependency_links.txt
src/selenium_profiles.egg-info/requires.txt
src/selenium_profiles.egg-info/top_level.txt
src/selenium_profiles/files/__init__.py
src/selenium_profiles/files/tmp/__init__.py
src/selenium_profiles/js/__init__.py
src/selenium_profiles/js/export_profile.js
src/selenium_profiles/js/fetch.js
src/selenium_profiles/js/undetected/__init.py
src/selenium_profiles/js/undetected/get_cdc_props.js
src/selenium_profiles/js/undetected/navigator_webdriver.js
src/selenium_profiles/js/undetected/remove_cdc_props.js
src/selenium_profiles/profiles/__init__.py
src/selenium_profiles/profiles/default.json
src/selenium_profiles/profiles/example.json
src/selenium_profiles/profiles/profiles.py
src/selenium_profiles/profiles/scratch.json
src/selenium_profiles/profiles/__pycache__/__init__.cpython-310.pyc
src/selenium_profiles/profiles/__pycache__/__init__.cpython-37.pyc
src/selenium_profiles/profiles/__pycache__/__init__.cpython-38.pyc
src/selenium_profiles/profiles/__pycache__/profiles.cpython-310.pyc
src/selenium_profiles/profiles/__pycache__/profiles.cpython-37.pyc
src/selenium_profiles/profiles/__pycache__/profiles.cpython-38.pyc
src/selenium_profiles/scripts/__init__.py
src/selenium_profiles/scripts/driver_utils.py
src/selenium_profiles/scripts/profiles.py
src/selenium_profiles/scripts/proxy.py
src/selenium_profiles/scripts/undetected.py
src/selenium_profiles/utils/__init__.py
src/selenium_profiles/utils/colab_utils.py
src/selenium_profiles/utils/utils.py
tests/test_driver.py