Metadata-Version: 2.1
Name: selenium-profiles
Version: 2.2.10
Summary: Emulate and Automate Chrome using Profiles and Selenium
Home-page: https://github.com/kaliiiiiiiiii/Selenium_Profiles
Author: Aurin Aegerter
Author-email: aurinliun@gmx.ch
Project-URL: Documentation, https://github.com/kaliiiiiiiiii/Selenium_Profiles
Project-URL: Bug Reports, https://github.com/kaliiiiiiiiii/Selenium_Profiles/issues
Project-URL: Source Code, https://github.com/kaliiiiiiiiii/Selenium_Profiles
Keywords: Selenium,emulation,automation,undetected-chromedriver,webautomation
Classifier: Development Status :: 2 - Pre-Alpha
Classifier: Intended Audience :: Developers
Classifier: Programming Language :: Python :: 3
Classifier: Programming Language :: Python :: 3.7
Classifier: Programming Language :: Python :: 3.8
Classifier: Programming Language :: Python :: 3.9
Classifier: Programming Language :: Python :: 3.10
Classifier: Programming Language :: Python :: 3.11
Classifier: License :: Free for non-commercial use
Classifier: Natural Language :: English
Classifier: Operating System :: OS Independent
Classifier: Framework :: Jupyter
Classifier: Topic :: Internet
Classifier: Topic :: Internet :: WWW/HTTP :: Browsers
Requires-Python: >=3.7
Provides-Extra: dev
License-File: LICENSE.md
